{"format":"CHIP-0007","name":"aminu maikudi","description":"aminu is a wealthy man from a family with generational wealth. His exquisite taste shows it","minting_tool":"TEAM CLUTCH","sensitive_content":false,"series_number":"33","series_total":420,"collection":{"name":"Zuri NFT Tickets for Free Lunch","id":"b774f676-c1d5-422e-beed-00ef5510c64d","attributes":[{"type":"description","value":"Rewards for accomplishments during HNGi9"}]},"gender":"male","uuid":"0129e7a5-e3d0-4675-92d0-1a1e55d11612","hash":"b975a6f5bc8f0d673f0ce5657029a634a62b9e251030e234bb64d75d3a30c3f3"}