{"format":"CHIP-0007","name":"bukola nosend","description":"Bukola is friends with many but always get moody.","minting_tool":"TEAM BOOT","sensitive_content":false,"series_number":"406","series_total":420,"collection":{"name":"Zuri NFT Tickets for Free Lunch","id":"b774f676-c1d5-422e-beed-00ef5510c64d","attributes":[{"type":"description","value":"Rewards for accomplishments during HNGi9"}]},"gender":"female","uuid":"59d19b13-09e2-412e-a669-df020e03ae10","hash":"f40a8301848620b73df8ee1112b7300411ccf2924bffb300d8641145185a7576"}